uun_windsurfguru/__init__.py
uun_windsurfguru/data/sample-config.json
uun_windsurfguru/data/start.sh
uun_windsurfguru/data/systemd.service
uun_windsurfguru/modules/WindSurfGuru.py
uun_windsurfguru/modules/__init__.py
uun_windsurfguru-0.2.6.data/scripts/uun-windsurfguru
uun_windsurfguru-0.2.6.data/scripts/uun-windsurfguru-install
uun_windsurfguru-0.2.6.data/scripts/uun-windsurfguru-setup
uun_windsurfguru-0.2.6.dist-info/LICENSE.md
uun_windsurfguru-0.2.6.dist-info/METADATA
uun_windsurfguru-0.2.6.dist-info/WHEEL
uun_windsurfguru-0.2.6.dist-info/top_level.txt
uun_windsurfguru-0.2.6.dist-info/RECORD
