Metadata-Version: 2.1
Name: uun-windsurfguru
Version: 0.2.6
Summary: Display wind surf conditions on a colorful LED strip.
Home-page: https://uuapp.plus4u.net/uu-bookkit-maing01/c145b7fe6d754775b71e196b3fbb9a6a/book/page?code=64720442
Author: (UUN) Tomáš Faikl & Marek Beránek
Author-email: tomas.faikl@unicornuniversity.net
Classifier: Programming Language :: Python :: 3
Classifier: License :: OSI Approved :: MIT License
Requires-Python: >=3.6
License-File: LICENSE.md
Requires-Dist: uun-iot >=0.10.0
Requires-Dist: uun-iot-libledstrip >=0.2.3
Provides-Extra: dev
Requires-Dist: uun-iot-libledstrip[dev] >=0.2.3 ; extra == 'dev'
Provides-Extra: gpio
Requires-Dist: uun-iot-libledstrip[gpio] >=0.2.3 ; extra == 'gpio'
Provides-Extra: neopixel
Requires-Dist: uun-iot-libledstrip[neopixel] >=0.2.3 ; extra == 'neopixel'
